pyrec.py
pyrec-0.2.1.dist-info/DESCRIPTION.rst
pyrec-0.2.1.dist-info/METADATA
pyrec-0.2.1.dist-info/metadata.json
pyrec-0.2.1.dist-info/RECORD
pyrec-0.2.1.dist-info/top_level.txt
pyrec-0.2.1.dist-info/WHEEL
