Metadata-Version: 2.0
Name: pyrec
Version: 0.2.1
Summary: A record datatype for Python
Home-page: https://github.com/bintoro/pyrec
Author: Kalle Tuure
Author-email: kalle@goodtimes.fi
License: MIT
Keywords: record,datatype,struct,namedtuple
Platform: UNKNOWN
Classifier: Programming Language :: Python
Classifier: Programming Language :: Python :: 2
Classifier: Programming Language :: Python :: 3
